README.md
setup.py
unit_ease/__init__.py
unit_ease/converters.py
unit_ease.egg-info/PKG-INFO
unit_ease.egg-info/SOURCES.txt
unit_ease.egg-info/dependency_links.txt
unit_ease.egg-info/top_level.txt