Metadata-Version: 2.1
Name: unit_ease
Version: 0.1
Summary: A simple unit converter package for length, temperature, weight, and volume conversions
Author: Hari K
Author-email: hariswdeveloper@gmail.com
Keywords: unit converter conversion length temperature weight volume
Classifier: Programming Language :: Python :: 3
Classifier: License :: OSI Approved :: MIT License
Classifier: Operating System :: OS Independent
Requires-Python: >=3.6
